itvalleyorion/__init__.py
itvalleyorion/orionsdk.py
itvalleyorion/agents/__init__.py
itvalleyorion/agents/chatbot.py
itvalleyorion/exemplos/__init__.py
itvalleyorion/exemplos/texttospeech.py
itvalleyorion/exemplos/transcribe.py
itvalleyorion/services/__init__.py
itvalleyorion/services/texttospeech.py
itvalleyorion/services/transcriptionaudio.py
itvalleyorion-0.1.2.dist-info/licenses/LICENSE
itvalleyorion-0.1.2.dist-info/METADATA
itvalleyorion-0.1.2.dist-info/WHEEL
itvalleyorion-0.1.2.dist-info/top_level.txt
itvalleyorion-0.1.2.dist-info/RECORD
