Metadata-Version: 2.4
Name: itvalleyorion
Version: 0.1.2
Summary: SDK para clientes e alunos da itvalley
Author-email: Carlos Viana <suporte@carlosviana.com>
License: MIT
Project-URL: Homepage, https://github.com/ITValley-School/orion-itvalley
Requires-Python: >=3.8
License-File: LICENSE
Requires-Dist: requests>=2.25.1
Dynamic: license-file
